CHANGES.txt
CONTRIBUTORS.txt
MANIFEST.in
README.md
README.txt
buildout.cfg
setup.py
versions.cfg
docs/LICENSE.GPL
docs/LICENSE.txt
src/imio/__init__.py
src/imio.urban.dataimport.egg-info/PKG-INFO
src/imio.urban.dataimport.egg-info/SOURCES.txt
src/imio.urban.dataimport.egg-info/dependency_links.txt
src/imio.urban.dataimport.egg-info/namespace_packages.txt
src/imio.urban.dataimport.egg-info/not-zip-safe
src/imio.urban.dataimport.egg-info/requires.txt
src/imio.urban.dataimport.egg-info/top_level.txt
src/imio/urban/__init__.py
src/imio/urban/dataimport/__init__.py
src/imio/urban/dataimport/config.py
src/imio/urban/dataimport/configure.zcml
src/imio/urban/dataimport/errormessage.py
src/imio/urban/dataimport/errors.py
src/imio/urban/dataimport/exceptions.py
src/imio/urban/dataimport/factory.py
src/imio/urban/dataimport/importer.py
src/imio/urban/dataimport/importsource.py
src/imio/urban/dataimport/interfaces.py
src/imio/urban/dataimport/mapper.py
src/imio/urban/dataimport/mapping.py
src/imio/urban/dataimport/profiles.zcml
src/imio/urban/dataimport/setuphandlers.py
src/imio/urban/dataimport/splitter.py
src/imio/urban/dataimport/testing.py
src/imio/urban/dataimport/testing.zcml
src/imio/urban/dataimport/utils.py
src/imio/urban/dataimport/AIHM/__init__.py
src/imio/urban/dataimport/AIHM/configure.zcml
src/imio/urban/dataimport/AIHM/importer.py
src/imio/urban/dataimport/AIHM/interfaces.py
src/imio/urban/dataimport/AIHM/mappers.py
src/imio/urban/dataimport/AIHM/objectsmapping.py
src/imio/urban/dataimport/AIHM/settings.py
src/imio/urban/dataimport/AIHM/valuesmapping.py
src/imio/urban/dataimport/MySQL/__init__.py
src/imio/urban/dataimport/MySQL/configure.zcml
src/imio/urban/dataimport/MySQL/importer.py
src/imio/urban/dataimport/MySQL/interfaces.py
src/imio/urban/dataimport/MySQL/mapper.py
src/imio/urban/dataimport/Postgres/__init__.py
src/imio/urban/dataimport/Postgres/configure.zcml
src/imio/urban/dataimport/Postgres/importer.py
src/imio/urban/dataimport/Postgres/interfaces.py
src/imio/urban/dataimport/Postgres/mapper.py
src/imio/urban/dataimport/access/__init__.py
src/imio/urban/dataimport/access/configure.zcml
src/imio/urban/dataimport/access/importer.py
src/imio/urban/dataimport/access/interfaces.py
src/imio/urban/dataimport/access/mapper.py
src/imio/urban/dataimport/access/settings.py
